Metadata-Version: 2.4
Name: wagtailvideos
Version: 7.1.0
Summary: A wagtail module for uploading and displaying videos in various codecs.
Home-page: https://github.com/neon-jungle/wagtailvideos
Author: Neon Jungle
Author-email: developers@neonjungle.studio
License: BSD License
Classifier: Environment :: Web Environment
Classifier: Intended Audience :: Developers
Classifier: Operating System :: OS Independent
Classifier: Programming Language :: Python
Classifier: Programming Language :: Python :: 3
Classifier: Programming Language :: Python :: 3.8
Classifier: Programming Language :: Python :: 3.9
Classifier: Programming Language :: Python :: 3.10
Classifier: Programming Language :: Python :: 3.11
Classifier: Programming Language :: Python :: 3.12
Classifier: Framework :: Django
Classifier: Framework :: Wagtail
Classifier: Framework :: Wagtail :: 6
Classifier: License :: OSI Approved :: BSD License
License-File: LICENSE
Requires-Dist: wagtail>=6.3
Requires-Dist: Django>=4.2
Requires-Dist: bcp47==0.0.4
Dynamic: author
Dynamic: author-email
Dynamic: classifier
Dynamic: description
Dynamic: home-page
Dynamic: license
Dynamic: license-file
Dynamic: requires-dist
Dynamic: summary
